armor/__init__.py
armor/cli.py
armor/client.py
armor/config.py
armor/exceptions.py
armor/models.py
armor/resources/__init__.py
armor/resources/alerts.py
armor/resources/api_keys.py
armor/resources/assets.py
armor/resources/base.py
armor/resources/freshness.py
armor/resources/lineage.py
armor/resources/schema.py
armor_cli-0.1.0.dist-info/METADATA
armor_cli-0.1.0.dist-info/WHEEL
armor_cli-0.1.0.dist-info/entry_points.txt
armor_cli-0.1.0.dist-info/RECORD
